CDC/__init__.py
CDC/__main__.py
CDC/color_models.py
CDC/orthomosaic_tiler.py
CDC/py.typed
CDC/tiled_color_based_distance.py
CDC/transforms.py
cdc-1.1.2.dist-info/METADATA
cdc-1.1.2.dist-info/WHEEL
cdc-1.1.2.dist-info/entry_points.txt
cdc-1.1.2.dist-info/licenses/LICENSE
cdc-1.1.2.dist-info/RECORD
